TikTokMarketing.py
__init__.py
TikTokMarketing-0.1.3.dist-info/METADATA
TikTokMarketing-0.1.3.dist-info/WHEEL
TikTokMarketing-0.1.3.dist-info/top_level.txt
TikTokMarketing-0.1.3.dist-info/RECORD
