Metadata-Version: 2.1
Name: TikTokMarketing
Version: 0.1.3
Summary: A package designed to connect to the TikTok Marketing API and return data to report on.
Author-email: Casper Crause <ccrause07@gmail.com>
Classifier: Programming Language :: Python :: 3
Classifier: License :: OSI Approved :: MIT License
Classifier: Operating System :: OS Independent
Requires-Python: >=3.10.0
